hiss/__init__.py
hiss/__main__.py
hiss/config.py
hiss/hiss_cli.py
hiss/parser.py
hiss/parsers/__init__.py
hiss/parsers/init.py
hiss/utils/__init__.py
hiss/utils/exceptions.py
hiss/utils/tools.py
hiss_cli-0.0.6.dist-info/DESCRIPTION.rst
hiss_cli-0.0.6.dist-info/METADATA
hiss_cli-0.0.6.dist-info/RECORD
hiss_cli-0.0.6.dist-info/WHEEL
hiss_cli-0.0.6.dist-info/entry_points.txt
hiss_cli-0.0.6.dist-info/metadata.json
hiss_cli-0.0.6.dist-info/top_level.txt
